{
  "version": 1,
  "parks": {
    "twisted_oaks": {
      "headings": {
        "j23": 187,
        "fm": 180,
        "ds": 209,
        "ruhmtrousers": 284,
        "mt": 203,
        "bt": 197,
        "ss": 221,
        "j1": 179,
        "rattrap": 222,
        "mj": 179,
        "j2": 89,
        "fx": 180
      },
      "order": [
        "mt",
        "ds",
        "j23",
        "fm",
        "ruhmtrousers",
        "j1",
        "bd",
        "hs",
        "rxc",
        "bxc",
        "blx",
        "rattrap",
        "bt",
        "ss",
        "mj",
        "j2",
        "fx",
        "bm",
        "tc",
        "je",
        "dz",
        "t1",
        "t2",
        "dm",
        "st",
        "gr",
        "mo",
        "pb",
        "or",
        "ab",
        "hp"
      ]
    },
    "phoenix": {
      "headings": {},
      "order": [
        "shop_west",
        "shop_east",
        "dj_side",
        "asgard"
      ]
    }
  }
}